{
  "realm": "alpha-bank-realm",
  "users": [
    {
      "username": "admin@alphabank.gr",
      "email": "admin@alphabank.gr",
      "firstName": "System",
      "lastName": "Administrator",
      "enabled": true,
      "emailVerified": true,
      "attributes": {
        "employeeId": ["EMP001"],
        "department": ["IT"],
        "jobTitle": ["System Administrator"],
        "tenant_id": ["11111111-1111-1111-1111-111111111111"],
        "preferredLanguage": ["en"]
      },
      "credentials": [
        {
          "type": "password",
          "value": "Admin@123",
          "temporary": false
        }
      ],
      "realmRoles": [
        "admin",
        "user"
      ]
    },
    {
      "username": "manager@alphabank.gr",
      "email": "manager@alphabank.gr",
      "firstName": "John",
      "lastName": "Manager",
      "enabled": true,
      "emailVerified": true,
      "attributes": {
        "employeeId": ["EMP002"],
        "department": ["Finance"],
        "jobTitle": ["Finance Manager"],
        "tenant_id": ["11111111-1111-1111-1111-111111111111"],
        "preferredLanguage": ["en"]
      },
      "credentials": [
        {
          "type": "password",
          "value": "Manager@123",
          "temporary": false
        }
      ],
      "realmRoles": [
        "manager",
        "user"
      ]
    },
    {
      "username": "user1@alphabank.gr",
      "email": "user1@alphabank.gr",
      "firstName": "Maria",
      "lastName": "Papadopoulos",
      "enabled": true,
      "emailVerified": true,
      "attributes": {
        "employeeId": ["EMP003"],
        "department": ["Finance"],
        "jobTitle": ["Financial Analyst"],
        "managerId": ["EMP002"],
        "tenant_id": ["11111111-1111-1111-1111-111111111111"],
        "preferredLanguage": ["el"]
      },
      "credentials": [
        {
          "type": "password",
          "value": "User@123",
          "temporary": false
        }
      ],
      "realmRoles": [
        "user"
      ]
    },
    {
      "username": "user2@alphabank.gr",
      "email": "user2@alphabank.gr",
      "firstName": "Dimitris",
      "lastName": "Nikolaou",
      "enabled": true,
      "emailVerified": true,
      "attributes": {
        "employeeId": ["EMP004"],
        "department": ["IT"],
        "jobTitle": ["Software Developer"],
        "tenant_id": ["11111111-1111-1111-1111-111111111111"],
        "preferredLanguage": ["en"]
      },
      "credentials": [
        {
          "type": "password",
          "value": "User@123",
          "temporary": false
        }
      ],
      "realmRoles": [
        "user"
      ]
    },
    {
      "username": "facility@alphabank.gr",
      "email": "facility@alphabank.gr",
      "firstName": "George",
      "lastName": "Facilities",
      "enabled": true,
      "emailVerified": true,
      "attributes": {
        "employeeId": ["EMP005"],
        "department": ["Operations"],
        "jobTitle": ["Facility Manager"],
        "tenant_id": ["11111111-1111-1111-1111-111111111111"],
        "preferredLanguage": ["en"]
      },
      "credentials": [
        {
          "type": "password",
          "value": "Facility@123",
          "temporary": false
        }
      ],
      "realmRoles": [
        "facility_manager",
        "user"
      ]
    },
    {
      "username": "hr@alphabank.gr",
      "email": "hr@alphabank.gr",
      "firstName": "Elena",
      "lastName": "HR",
      "enabled": true,
      "emailVerified": true,
      "attributes": {
        "employeeId": ["EMP006"],
        "department": ["Human Resources"],
        "jobTitle": ["HR Manager"],
        "tenant_id": ["11111111-1111-1111-1111-111111111111"],
        "preferredLanguage": ["el"]
      },
      "credentials": [
        {
          "type": "password",
          "value": "HR@123",
          "temporary": false
        }
      ],
      "realmRoles": [
        "hr",
        "user"
      ]
    }
  ]
}
